lettria/__init__.py
lettria/client.py
lettria/data.py
lettria/extractClass.py
lettria/sentence.py
lettria/sharedClass.py
lettria/subClasses.py
lettria-3.0.0.dist-info/DESCRIPTION.rst
lettria-3.0.0.dist-info/METADATA
lettria-3.0.0.dist-info/RECORD
lettria-3.0.0.dist-info/WHEEL
lettria-3.0.0.dist-info/metadata.json
lettria-3.0.0.dist-info/top_level.txt
