Metadata-Version: 2.0
Name: lettria
Version: 3.0.0
Summary: Lettria official SDK for python
Home-page: https://github.com/Lettria/sdk-python
Author: Victor
Author-email: victor@lettria.com
License: MIT
Keywords: lettria french nlp taln chatbot bigdata text analysis
Platform: UNKNOWN
Requires-Dist: requests (>=2.10)
